{
  "build": {
    "distDir": []
  },
  "package": {
    "productName": "fig_desktop"
  },
  "tauri": {
    "allowlist": {},
    "bundle": {
      "targets": "app",
      "active": true,
      "identifier": "com.mschrage.fig",
      "icon": [
        "icons/128x128.png",
        "icons/128x128@2x.png",
        "icons/16x16.png",
        "icons/16x16@2x.png",
        "icons/256x256.png",
        "icons/256x256@2x.png",
        "icons/32x32.png",
        "icons/32x32@2x.png",
        "icons/512x512.png",
        "icons/512x512@2x.png"
      ],
      "resources": [],
      "category": "DeveloperTool"
    },
    "security": {},
    "updater": {},
    "windows": []
  }
}
